{
    "heading": "Our sectors",
    "items": [{
        "logo": {
            "url": "cms-images/sector/sector-1.png",
            "alt": "Commodities"
        },
        "title": "Commodities",
        "description": "Supporting strategic planning activities, product research and investment decisions through timely news and comprehensive business intelligence on:",
        "products": ["Crop", "livestock", "Meat", "Poultry", "Dairy", "Energy", "Biofuels"],
        "cta": {
            "link": "#",
            "label": "More"
        }

    }, {
        "logo": {
            "url": "cms-images/sector/sector-2.png",
            "alt": "Crop Protection"
        },
        "title": "Crop protection",
        "description": "Supporting strategic planning activities, product research and investment decisions through timely news and comprehensive business intelligence on:",
        "products": ["Global agrochemical", "Seed", "Biotechnology markets"],
        "cta": {
            "link": "#",
            "label": "More"
        }

    }, {
        "logo": {
            "url": "cms-images/sector/sector-3.png",
            "alt": "Fertilizers"
        },
        "title": "Fertilizers",
        "description": "Enhancing revenue growth with the most accurate and forward looking information available on fertilizers and fertilizer raw materials",
        "products": ["Ammonia", "Nitrogen", "Phosphates", "Urea", "Potash", "Sulphuric Acid"],
        "cta": {
            "link": "#",
            "label": "More"
        }
    }, {
        "logo": {
            "url": "cms-images/sector/sector-4.png",
            "alt": "Animal Health"
        },
        "title": "Animal health",
        "description": "Providing our customers with unrivalled news, data and analysis on:",
        "products": ["Animal Health", "Nutrition Regulations", " Products", "Technologies Emerging Trends on a global scale"],
        "cta": {
            "link": "#",
            "label": "More"
        }
    }, {
        "logo": {
            "url": "cms-images/sector/sector-5.png",
            "alt": "Agricultural food policy & regulation"
        },
        "title": "Agricultural food policy & regulation",
        "description": "Supplying business-critical news, analysis, insight and reference data on international food law and agricultural policy",
        "products": ["Crop", "livestock", "Meat", "Poultry", "Dairy", "Energy", "Biofuels"],
        "cta": {
            "link": "#",
            "label": "More"
        }
    }]
}
